converter/__init__.py
converter/converter.py
lance_image_converter-0.1.0.dist-info/METADATA
lance_image_converter-0.1.0.dist-info/WHEEL
lance_image_converter-0.1.0.dist-info/entry_points.txt
lance_image_converter-0.1.0.dist-info/top_level.txt
lance_image_converter-0.1.0.dist-info/RECORD
