Metadata-Version: 2.1
Name: lance-image-converter
Version: 0.1.0
Summary: A package to convert image datasets to Lance format
Home-page: https://github.com/lancedb/lance-deeplearning-recipes/tree/main/converters/lance-image-dataset-converter
Author: Vipul Maheshwari
Author-email: vim.code.level@gmail.com
Classifier: Programming Language :: Python :: 3
Classifier: License :: OSI Approved :: MIT License
Classifier: Operating System :: OS Independent
Requires-Python: >=3.6
Requires-Dist: pyarrow
Requires-Dist: pillow
Requires-Dist: tqdm
Requires-Dist: lance
Requires-Dist: pandas
Requires-Dist: lancedb
